letsgoing_rpi_arduinocontrol/Config.py
letsgoing_rpi_arduinocontrol/Controller.py
letsgoing_rpi_arduinocontrol/Gui.py
letsgoing_rpi_arduinocontrol/Singleton.py
letsgoing_rpi_arduinocontrol/SuperButton.py
letsgoing_rpi_arduinocontrol/Video.py
letsgoing_rpi_arduinocontrol/__init__.py
letsgoing_rpi_arduinocontrol/__main__.py
letsgoing_rpi_arduinocontrol/resources/Button-off.gif
letsgoing_rpi_arduinocontrol/resources/Button-on.gif
letsgoing_rpi_arduinocontrol/resources/LED_red-off.gif
letsgoing_rpi_arduinocontrol/resources/LED_red-on.gif
letsgoing_rpi_arduinocontrol/resources/Switch-off.gif
letsgoing_rpi_arduinocontrol/resources/Switch-on.gif
letsgoing_rpi_arduinocontrol/resources/__init__.py
letsgoing_rpi_arduinocontrol/resources/config.json
letsgoing_rpi_arduinocontrol/resources/default_pinconfig.txt
letsgoing_rpi_arduinocontrol-0.0.3.dist-info/LICENSE
letsgoing_rpi_arduinocontrol-0.0.3.dist-info/METADATA
letsgoing_rpi_arduinocontrol-0.0.3.dist-info/WHEEL
letsgoing_rpi_arduinocontrol-0.0.3.dist-info/entry_points.txt
letsgoing_rpi_arduinocontrol-0.0.3.dist-info/top_level.txt
letsgoing_rpi_arduinocontrol-0.0.3.dist-info/RECORD
