Metadata-Version: 2.1
Name: letsgoing-rpi-arduinocontrol
Version: 0.0.3
Summary: GUI for control of Arduino IO from Raspberry Pi
Home-page: https://github.com/tobiglaser/letsgoing-rpi-arduinocontrol
Author: Tobias Glaser
Classifier: Programming Language :: Python :: 3
Classifier: License :: OSI Approved :: GNU General Public License v2 (GPLv2)
Classifier: Operating System :: POSIX :: Linux
Requires-Python: >=3.7
License-File: LICENSE
Requires-Dist: adafruit-circuitpython-ds3502
Requires-Dist: adafruit-circuitpython-mcp230xx
Requires-Dist: python-vlc
Requires-Dist: Pillow
Requires-Dist: tkinter
